flytekitplugins_notebook-0.1.0-py3.8-nspkg.pth
flytekitplugins/notebook/__init__.py
flytekitplugins/notebook/task.py
flytekitplugins_notebook-0.1.0.dist-info/METADATA
flytekitplugins_notebook-0.1.0.dist-info/WHEEL
flytekitplugins_notebook-0.1.0.dist-info/namespace_packages.txt
flytekitplugins_notebook-0.1.0.dist-info/top_level.txt
flytekitplugins_notebook-0.1.0.dist-info/RECORD
