Metadata-Version: 2.1
Name: flytekitplugins-notebook
Version: 0.1.0
Summary: Your microlib descriton
Home-page: UNKNOWN
Author: flyteorg
Author-email: admin@flyte.org
License: apache2
Platform: UNKNOWN
Classifier: Intended Audience :: Science/Research
Classifier: Intended Audience :: Developers
Classifier: License :: OSI Approved :: Apache Software License
Classifier: Programming Language :: Python :: 3.7
Classifier: Programming Language :: Python :: 3.8
Classifier: Topic :: Scientific/Engineering
Classifier: Topic :: Scientific/Engineering :: Artificial Intelligence
Classifier: Topic :: Software Development
Classifier: Topic :: Software Development :: Libraries
Classifier: Topic :: Software Development :: Libraries :: Python Modules
Requires-Python: >=3.7
Requires-Dist: flytekit (==0.16.0a2)
Requires-Dist: papermill (>=1.2.0)
Requires-Dist: nbconvert (>=6.0.7)
Requires-Dist: ipykernel (>=5.0.0)
